lazyscribe_arrow/__init__.py
lazyscribe_arrow/_meta.py
lazyscribe_arrow/csv.py
lazyscribe_arrow/interchange.py
lazyscribe_arrow/parquet.py
lazyscribe_arrow/protocols.py
lazyscribe_arrow-0.3.1.dist-info/WHEEL
lazyscribe_arrow-0.3.1.dist-info/entry_points.txt
lazyscribe_arrow-0.3.1.dist-info/METADATA
lazyscribe_arrow-0.3.1.dist-info/RECORD
