Metadata-Version: 2.3
Name: lazyscribe-arrow
Version: 0.3.1
Summary: Arrow-based artifact handlers for Lazyscribe
Author: Akshay Gupta
Author-email: Akshay Gupta <akgcodes@gmail.com>
License: MIT license
Classifier: Development Status :: 3 - Alpha
Classifier: License :: OSI Approved :: MIT License
Classifier: Natural Language :: English
Classifier: Programming Language :: Python :: 3 :: Only
Classifier: Programming Language :: Python :: 3.10
Classifier: Programming Language :: Python :: 3.11
Classifier: Programming Language :: Python :: 3.12
Classifier: Programming Language :: Python :: 3.13
Requires-Dist: attrs>=21.2,<=25.4
Requires-Dist: lazyscribe>=2,<3
Requires-Dist: pyarrow>=14.0.1,<=23
Requires-Dist: python-slugify>=5,<=8.0.4
Requires-Dist: commitizen ; extra == 'build'
Requires-Dist: uv ; extra == 'build'
Requires-Dist: lazyscribe-arrow[build] ; extra == 'dev'
Requires-Dist: lazyscribe-arrow[qa] ; extra == 'dev'
Requires-Dist: lazyscribe-arrow[tests] ; extra == 'dev'
Requires-Dist: edgetest ; extra == 'qa'
Requires-Dist: mypy ; extra == 'qa'
Requires-Dist: pre-commit ; extra == 'qa'
Requires-Dist: pyproject-fmt ; extra == 'qa'
Requires-Dist: ruff ; extra == 'qa'
Requires-Dist: types-python-slugify ; extra == 'qa'
Requires-Dist: uv ; extra == 'qa'
Requires-Dist: pandas ; extra == 'tests'
Requires-Dist: pytest ; extra == 'tests'
Requires-Dist: pytest-cov ; extra == 'tests'
Requires-Dist: time-machine ; extra == 'tests'
Requires-Python: >=3.10.0
Project-URL: Documentation, https://github.com/lazyscribe/lazyscribe-arrow
Project-URL: Repository, https://github.com/lazyscribe/lazyscribe-arrow
Provides-Extra: build
Provides-Extra: dev
Provides-Extra: qa
Provides-Extra: tests
